wolf_hunter/__init__.py
wolf_hunter/core.py
wolf_hunter/reporter.py
wolf_hunter/scanners.py
wolf_hunter/templates/report.html
cyber_wolf_hunter-1.0.1.dist-info/METADATA
cyber_wolf_hunter-1.0.1.dist-info/WHEEL
cyber_wolf_hunter-1.0.1.dist-info/top_level.txt
cyber_wolf_hunter-1.0.1.dist-info/RECORD
