Metadata-Version: 2.4
Name: cyber-wolf-hunter
Version: 1.0.1
Summary: Comprehensive website vulnerability scanner with multi-threading and HTML reporting
Home-page: https://github.com/Tamilselvan-S-Cyber-Security/cyber-wolf-hunter
Author: S.Tamilselvan
Author-email: tamilselvanreacher@gmail.com
Project-URL: Bug Reports, https://github.com/Tamilselvan-S-Cyber-Security/cyberwolf-hunter/issues
Project-URL: Source, https://github.com/Tamilselvan-S-Cyber-Security/cyber-wolf-hunter
Project-URL: Documentation, https://github.com/Tamilselvan-S-Cyber-Security/cyber-wolf-hunter/wiki
Project-URL: Portfolio, https://tamilselvan-portfolio-s.web.app/
Keywords: cybersecurity,vulnerability scanner,web security,penetration testing,security assessment
Classifier: Development Status :: 5 - Production/Stable
Classifier: Intended Audience :: Developers
Classifier: Intended Audience :: Information Technology
Classifier: License :: OSI Approved :: MIT License
Classifier: Operating System :: OS Independent
Classifier: Programming Language :: Python :: 3
Classifier: Programming Language :: Python :: 3.7
Classifier: Programming Language :: Python :: 3.8
Classifier: Programming Language :: Python :: 3.9
Classifier: Programming Language :: Python :: 3.10
Classifier: Topic :: Security
Classifier: Topic :: Software Development :: Libraries :: Python Modules
Classifier: Topic :: System :: Networking :: Monitoring
Requires-Python: >=3.7
Requires-Dist: requests>=2.25.0
Requires-Dist: beautifulsoup4>=4.9.0
Requires-Dist: jinja2>=3.0.0
Requires-Dist: urllib3>=1.26.0
Provides-Extra: dev
Requires-Dist: pytest>=6.0; extra == "dev"
Requires-Dist: black>=21.0; extra == "dev"
Requires-Dist: flake8>=3.8; extra == "dev"
Dynamic: author
Dynamic: author-email
Dynamic: classifier
Dynamic: description
Dynamic: description-content-type
Dynamic: home-page
Dynamic: keywords
Dynamic: project-url
Dynamic: provides-extra
Dynamic: requires-dist
Dynamic: requires-python
Dynamic: summary
